setup.py
difflib_chubak/__init__.py
difflib_chubak/one.py
difflib_chubak/two.py
difflib_chubak.egg-info/PKG-INFO
difflib_chubak.egg-info/SOURCES.txt
difflib_chubak.egg-info/dependency_links.txt
difflib_chubak.egg-info/top_level.txt