Metadata-Version: 2.1
Name: difflib-chubak
Version: 0.0.1
Summary: My Package
Author: Chubak
Author-email: 104@mail.com
